tfa_car.py
tfa_car-0.1.1.dist-info/LICENSE.md
tfa_car-0.1.1.dist-info/WHEEL
tfa_car-0.1.1.dist-info/METADATA
tfa_car-0.1.1.dist-info/RECORD
